example/__init__.py
example/anal_result.py
example/classification_test.py
example/cnn_test.py
example/load_test.py
example/regression_test.py
jjy/__init__.py
jjy/dataset/__init__.py
jjy/dataset/mnist.py
jjy/framework/__init__.py
jjy/framework/functions.py
jjy/framework/gradient.py
jjy/framework/initializer.py
jjy/framework/layer.py
jjy/framework/network.py
jjy/framework/optimizer.py
jjy/framework/scaler.py
example_pkg_jjy37777-0.0.1.dist-info/METADATA
example_pkg_jjy37777-0.0.1.dist-info/WHEEL
example_pkg_jjy37777-0.0.1.dist-info/top_level.txt
example_pkg_jjy37777-0.0.1.dist-info/RECORD
