Metadata-Version: 2.1
Name: example-pkg-jjy37777
Version: 0.0.1
Summary: jjy ai framework
Home-page: https://github.com/woduq1414/deep-learning-without-framework
Author: jjy37777
Author-email: jjy37777@naver.com
License: UNKNOWN
Platform: UNKNOWN
Classifier: Programming Language :: Python :: 3
Classifier: License :: OSI Approved :: MIT License
Classifier: Operating System :: OS Independent
Requires-Python: >=3.6
